stickydesign_accel-0.9.2.dist-info/METADATA
stickydesign_accel-0.9.2.dist-info/WHEEL
stickydesign_accel/__init__.py
stickydesign_accel/stickydesign_accel.cpython-313-x86_64-linux-gnu.so
stickydesign_accel-0.9.2.dist-info/RECORD
